Metadata-Version: 1.0
Name: ml-pyxis
Version: 0.4.dev0
Summary: Tool for reading and writing datasets of tensors with MessagePack and Lightning Memory-Mapped Database (LMDB)
Home-page: https://github.com/vicolab/ml-pyxis
Author: Igor Barros Barbosa and Aleksander Rognhaugen
Author-email: UNKNOWN
License: MIT
Platform: UNKNOWN
